design.sv
module johnson_counter (
    input clk,
    input reset,
    output reg [3:0] out
);

always @(posedge clk or posedge reset) begin
    if (reset)
        out <= 4'b0000;
    else
        out <= {~out[3], out[3:1]}; 
end

endmodule

testbench.sv
module tb_johnson_counter;
    reg clk, reset;
    wire [3:0] out;

    johnson_counter uut (
        .clk(clk),
        .reset(reset),
        .out(out)
    );

    initial begin
        clk = 0;
        forever #5 clk = ~clk; 
    end

    initial begin
        reset = 1;
        #10 reset = 0;
        #100 $finish;
    end

    initial begin
      $dumpfile("johnson_counter.vcd");
      $dumpvars;
        $monitor("Time = %0t | Output = %b", $time, out);
    end
endmodule

johnson_counter.vcd
$date
	Tue Jul 29 10:02:21 2025
$end
$version
	Icarus Verilog
$end
$timescale
	1s
$end
$scope module tb_johnson_counter $end
$var wire 4 ! out [3:0] $end
$var reg 1 " clk $end
$var reg 1 # reset $end
$scope module uut $end
$var wire 1 " clk $end
$var wire 1 # reset $end
$var reg 4 $ out [3:0] $end
$upscope $end
$upscope $end
$enddefinitions $end
$comment Show the parameter values. $end
$dumpall
$end
#0
$dumpvars
b0 $
1#
0"
b0 !
$end
#5
1"
#10
0"
0#
#15
b1000 !
b1000 $
1"
#20
0"
#25
b100 !
b100 $
1"
#30
0"
#35
b1010 !
b1010 $
1"
#40
0"
#45
b101 !
b101 $
1"
#50
0"
#55
b1010 !
b1010 $
1"
#60
0"
#65
b101 !
b101 $
1"
#70
0"
#75
b1010 !
b1010 $
1"
#80
0"
#85
b101 !
b101 $
1"
#90
0"
#95
b1010 !
b1010 $
1"
#100
0"
#105
b101 !
b101 $
1"
